smithy_aws_core/__init__.py
smithy_aws_core/identity.py
smithy_aws_core/py.typed
smithy_aws_core/interfaces/__init__.py
smithy_core/__init__.py
smithy_core/deserializers.py
smithy_core/documents.py
smithy_core/exceptions.py
smithy_core/identity.py
smithy_core/interceptors.py
smithy_core/prelude.py
smithy_core/py.typed
smithy_core/retries.py
smithy_core/rfc3986.py
smithy_core/schemas.py
smithy_core/serializers.py
smithy_core/shapes.py
smithy_core/traits.py
smithy_core/types.py
smithy_core/utils.py
smithy_core/aio/__init__.py
smithy_core/aio/types.py
smithy_core/aio/utils.py
smithy_core/aio/interfaces/__init__.py
smithy_core/aio/interfaces/identity.py
smithy_core/interfaces/__init__.py
smithy_core/interfaces/exceptions.py
smithy_core/interfaces/identity.py
smithy_core/interfaces/retries.py
smithy_http/__init__.py
smithy_http/endpoints.py
smithy_http/exceptions.py
smithy_http/py.typed
smithy_http/restjson.py
smithy_http/utils.py
smithy_http/aio/__init__.py
smithy_http/aio/aiohttp.py
smithy_http/aio/crt.py
smithy_http/aio/endpoints.py
smithy_http/aio/restjson.py
smithy_http/aio/auth/__init__.py
smithy_http/aio/auth/apikey.py
smithy_http/aio/identity/__init__.py
smithy_http/aio/identity/apikey.py
smithy_http/aio/interfaces/__init__.py
smithy_http/aio/interfaces/auth.py
smithy_http/interfaces/__init__.py
smithy_json/__init__.py
smithy_json/py.typed
svectordb/__init__.py
svectordb/auth.py
svectordb/client.py
svectordb/config.py
svectordb/deserialize.py
svectordb/errors.py
svectordb/models.py
svectordb/serialize.py
svectordb/_private/__init__.py
svectordb/_private/schemas.py
svectordb-0.0.9.dist-info/METADATA
svectordb-0.0.9.dist-info/WHEEL
svectordb-0.0.9.dist-info/top_level.txt
svectordb-0.0.9.dist-info/RECORD
